setup.py
torch_lfilter.cpp
torch_lfilter.py
torch_lfilter.egg-info/PKG-INFO
torch_lfilter.egg-info/SOURCES.txt
torch_lfilter.egg-info/dependency_links.txt
torch_lfilter.egg-info/top_level.txt