Metadata-Version: 2.1
Name: torch-lfilter
Version: 0.0.3
Summary:  Bring lowpass filtering to PyTorch! 
Home-page: https://github.com/flaport/torch_lfilter
Author: Floris Laporte
Author-email: floris.laporte@gmail.com
License: UNKNOWN
Platform: UNKNOWN
Classifier: Programming Language :: Python :: 3
Classifier: Operating System :: OS Independent
Classifier: Topic :: Scientific/Engineering :: Mathematics
Classifier: License :: OSI Approved :: GNU General Public License v3 (GPLv3)
